README.rst
setup.py
bin/compare_versions
compare_versions/__init__.py
compare_versions/__main__.py
compare_versions/core.py
compare_versions/version.py
compare_versions.egg-info/PKG-INFO
compare_versions.egg-info/SOURCES.txt
compare_versions.egg-info/dependency_links.txt
compare_versions.egg-info/top_level.txt
compare_versions/schemes/__init__.py
compare_versions/schemes/_string.py
compare_versions/schemes/base.py
compare_versions/schemes/semver.py