Metadata-Version: 1.1
Name: compare-versions
Version: 0.2.0
Summary: Compare versions using various versioning schemes
Home-page: https://github.com/lukeyeager/compare-versions
Author: Luke Yeager
Author-email: luke.yeager@gmail.com
License: UNKNOWN
Platform: UNKNOWN
Classifier: License :: OSI Approved :: MIT License
Classifier: Operating System :: OS Independent
Classifier: Programming Language :: Python
